ltm_misc/__init__.py
ltm_misc/process.py
ltm_misc/process.pyi
ltm_misc-2.2.dist-info/LICENSE
ltm_misc-2.2.dist-info/METADATA
ltm_misc-2.2.dist-info/WHEEL
ltm_misc-2.2.dist-info/top_level.txt
ltm_misc-2.2.dist-info/RECORD
